exception_template/__init__.py
exception_template/exception_template.py
exception_template-1.0.0.dist-info/DESCRIPTION.rst
exception_template-1.0.0.dist-info/METADATA
exception_template-1.0.0.dist-info/RECORD
exception_template-1.0.0.dist-info/WHEEL
exception_template-1.0.0.dist-info/metadata.json
exception_template-1.0.0.dist-info/top_level.txt
