Metadata-Version: 2.0
Name: exception-template
Version: 1.0.0
Summary: Create exception classes from message templates.
Home-page: https://github.com/rcfox/exception-template
Author: Ryan Fox
Author-email: ryan@rcfox.ca
License: MIT
Platform: UNKNOWN
Classifier: License :: OSI Approved :: MIT License
Classifier: Programming Language :: Python :: 3
Classifier: Programming Language :: Python :: 3.7
Classifier: Typing :: Typed
